{"name": "5\u5934\u6ef4\u5b9a\u6cf5WiFi_BLE", "packetVersion": "0x00000004", "protocolType": "standard", "product_key": "5ab6019f2dbb4ae7a42b48d2b8ce0530", "entities": [{"display_name": "\u673a\u667a\u4e91\u5f00\u53d1\u5957\u4ef6", "attrs": [{"display_name": "\u5f00\u5173", "name": "switch", "data_type": "bool", "position": {"byte_offset": 0, "unit": "bit", "len": 1, "bit_offset": 0}, "type": "status_writable", "id": 0, "desc": ""}, {"display_name": "\u901a\u90531", "name": "channe1", "data_type": "bool", "position": {"byte_offset": 0, "unit": "bit", "len": 1, "bit_offset": 1}, "type": "status_writable", "id": 1, "desc": "\u901a\u90531\u624b\u52a8\u5f00\u5173"}, {"display_name": "\u901a\u90532", "name": "channe2", "data_type": "bool", "position": {"byte_offset": 0, "unit": "bit", "len": 1, "bit_offset": 2}, "type": "status_writable", "id": 2, "desc": "\u901a\u90532\u624b\u52a8\u5f00\u5173"}, {"display_name": "\u901a\u90533", "name": "channe3", "data_type": "bool", "position": {"byte_offset": 0, "unit": "bit", "len": 1, "bit_offset": 3}, "type": "status_writable", "id": 3, "desc": "\u901a\u90533\u624b\u52a8\u5f00\u5173"}, {"display_name": "\u901a\u90534", "name": "channe4", "data_type": "bool", "position": {"byte_offset": 0, "unit": "bit", "len": 1, "bit_offset": 4}, "type": "status_writable", "id": 4, "desc": "\u901a\u90534\u624b\u52a8\u5f00\u5173"}, {"display_name": "\u901a\u90535", "name": "channe5", "data_type": "bool", "position": {"byte_offset": 0, "unit": "bit", "len": 1, "bit_offset": 5}, "type": "status_writable", "id": 5, "desc": "\u901a\u90535\u624b\u52a8\u5f00\u5173"}, {"display_name": "\u901a\u90536", "name": "channe6", "data_type": "bool", "position": {"byte_offset": 0, "unit": "bit", "len": 1, "bit_offset": 6}, "type": "status_writable", "id": 6, "desc": "\u901a\u90536\u624b\u52a8\u5f00\u5173"}, {"display_name": "\u901a\u90537", "name": "channe7", "data_type": "bool", "position": {"byte_offset": 0, "unit": "bit", "len": 1, "bit_offset": 7}, "type": "status_writable", "id": 7, "desc": "\u901a\u90537\u624b\u52a8\u5f00\u5173"}, {"display_name": "\u901a\u90538", "name": "channe8", "data_type": "bool", "position": {"byte_offset": 0, "unit": "bit", "len": 1, "bit_offset": 8}, "type": "status_writable", "id": 8, "desc": "\u901a\u90538\u624b\u52a8\u5f00\u5173"}, {"display_name": "\u5b9a\u65f6\u5f00\u51731", "name": "Timer1ON", "data_type": "bool", "position": {"byte_offset": 0, "unit": "bit", "len": 1, "bit_offset": 9}, "type": "status_writable", "id": 9, "desc": "\u5b9a\u65f6\u56681\u5f00\u5173\uff0c0\uff1a\u5173\u95ed\uff0c1\uff1a\u5b9a\u65f6"}, {"display_name": "\u5b9a\u65f6\u5f00\u51732", "name": "Timer2ON", "data_type": "bool", "position": {"byte_offset": 0, "unit": "bit", "len": 1, "bit_offset": 10}, "type": "status_writable", "id": 10, "desc": "\u5b9a\u65f6\u56682\u5f00\u5173\uff0c0\uff1a\u5173\u95ed\uff0c1\uff1a\u5b9a\u65f6"}, {"display_name": "\u5b9a\u65f6\u5f00\u51733", "name": "Timer3ON", "data_type": "bool", "position": {"byte_offset": 0, "unit": "bit", "len": 1, "bit_offset": 11}, "type": "status_writable", "id": 11, "desc": "\u5b9a\u65f6\u56683\u5f00\u5173\uff0c0\uff1a\u5173\u95ed\uff0c1\uff1a\u5b9a\u65f6"}, {"display_name": "\u5b9a\u65f6\u5f00\u51734", "name": "Timer4ON", "data_type": "bool", "position": {"byte_offset": 0, "unit": "bit", "len": 1, "bit_offset": 12}, "type": "status_writable", "id": 12, "desc": "\u5b9a\u65f6\u56684\u5f00\u5173\uff0c0\uff1a\u5173\u95ed\uff0c1\uff1a\u5b9a\u65f6"}, {"display_name": "\u5b9a\u65f6\u5f00\u51735", "name": "Timer5ON", "data_type": "bool", "position": {"byte_offset": 0, "unit": "bit", "len": 1, "bit_offset": 13}, "type": "status_writable", "id": 13, "desc": "\u5b9a\u65f6\u56685\u5f00\u5173\uff0c0\uff1a\u5173\u95ed\uff0c1\uff1a\u5b9a\u65f6"}, {"display_name": "\u5b9a\u65f6\u5f00\u51736", "name": "Timer6ON", "data_type": "bool", "position": {"byte_offset": 0, "unit": "bit", "len": 1, "bit_offset": 14}, "type": "status_writable", "id": 14, "desc": "\u5b9a\u65f6\u56686\u5f00\u5173\uff0c0\uff1a\u5173\u95ed\uff0c1\uff1a\u5b9a\u65f6"}, {"display_name": "\u5b9a\u65f6\u5f00\u51737", "name": "Timer7ON", "data_type": "bool", "position": {"byte_offset": 0, "unit": "bit", "len": 1, "bit_offset": 15}, "type": "status_writable", "id": 15, "desc": "\u5b9a\u65f6\u56687\u5f00\u5173\uff0c0\uff1a\u5173\u95ed\uff0c1\uff1a\u5b9a\u65f6"}, {"display_name": "\u5b9a\u65f6\u5f00\u51738", "name": "Timer8ON", "data_type": "bool", "position": {"byte_offset": 0, "unit": "bit", "len": 1, "bit_offset": 16}, "type": "status_writable", "id": 16, "desc": "\u5b9a\u65f6\u56688\u5f00\u5173\uff0c0\uff1a\u5173\u95ed\uff0c1\uff1a\u5b9a\u65f6"}, {"display_name": "\u6821\u51c6\u5f00\u5173", "name": "CALSW", "data_type": "bool", "position": {"byte_offset": 0, "unit": "bit", "len": 1, "bit_offset": 17}, "type": "status_writable", "id": 17, "desc": "\u6821\u51c6\u5f00\u5173"}, {"display_name": "\u6821\u51c6\u901a\u9053", "name": "CALSet", "data_type": "enum", "enum": ["\u6821\u51c61", "\u6821\u51c62", "\u6821\u51c63", "\u6821\u51c64", "\u6821\u51c65", "\u6821\u51c66", "\u6821\u51c67", "\u6821\u51c68"], "position": {"byte_offset": 0, "unit": "bit", "len": 3, "bit_offset": 18}, "type": "status_writable", "id": 18, "desc": "0:\u6821\u51c61;1:\u6821\u51c62\uff1b2:\u6821\u51c63\uff1b3:\u6821\u51c64;4:\u6821\u51c65;5:\u6821\u51c66\uff1b6:\u6821\u51c67\uff1b7:\u6821\u51c68"}, {"display_name": "\u5934\u6570\u91cf", "name": "channelTTL", "data_type": "uint8", "position": {"byte_offset": 3, "unit": "byte", "len": 1, "bit_offset": 0}, "uint_spec": {"addition": 0, "max": 8, "ratio": 1, "min": 1}, "type": "status_writable", "id": 19, "desc": "\u5934\u6570\u91cf"}, {"display_name": "\u95f4\u9699\u65f6\u95f41", "name": "IntervalT1", "data_type": "uint8", "position": {"byte_offset": 4, "unit": "byte", "len": 1, "bit_offset": 0}, "uint_spec": {"addition": 0, "max": 30, "ratio": 1, "min": 0}, "type": "status_writable", "id": 20, "desc": "\u901a\u90531\u95f4\u9699\u65f6\u95f4"}, {"display_name": "\u95f4\u9699\u65f6\u95f42", "name": "IntervalT2", "data_type": "uint8", "position": {"byte_offset": 5, "unit": "byte", "len": 1, "bit_offset": 0}, "uint_spec": {"addition": 0, "max": 30, "ratio": 1, "min": 0}, "type": "status_writable", "id": 21, "desc": "\u901a\u90532\u95f4\u9699\u65f6\u95f4"}, {"display_name": "\u95f4\u9699\u65f6\u95f43", "name": "IntervalT3", "data_type": "uint8", "position": {"byte_offset": 6, "unit": "byte", "len": 1, "bit_offset": 0}, "uint_spec": {"addition": 0, "max": 30, "ratio": 1, "min": 0}, "type": "status_writable", "id": 22, "desc": "\u901a\u90533\u95f4\u9699\u65f6\u95f4"}, {"display_name": "\u95f4\u9699\u65f6\u95f44", "name": "IntervalT4", "data_type": "uint8", "position": {"byte_offset": 7, "unit": "byte", "len": 1, "bit_offset": 0}, "uint_spec": {"addition": 0, "max": 30, "ratio": 1, "min": 0}, "type": "status_writable", "id": 23, "desc": "\u901a\u90534\u95f4\u9699\u65f6\u95f4"}, {"display_name": "\u95f4\u9699\u65f6\u95f45", "name": "IntervalT5", "data_type": "uint8", "position": {"byte_offset": 8, "unit": "byte", "len": 1, "bit_offset": 0}, "uint_spec": {"addition": 0, "max": 30, "ratio": 1, "min": 0}, "type": "status_writable", "id": 24, "desc": "\u901a\u90535\u95f4\u9699\u65f6\u95f4"}, {"display_name": "\u95f4\u9699\u65f6\u95f46", "name": "IntervalT6", "data_type": "uint8", "position": {"byte_offset": 9, "unit": "byte", "len": 1, "bit_offset": 0}, "uint_spec": {"addition": 0, "max": 30, "ratio": 1, "min": 0}, "type": "status_writable", "id": 25, "desc": "\u901a\u90536\u95f4\u9699\u65f6\u95f4"}, {"display_name": "\u95f4\u9699\u65f6\u95f47", "name": "IntervalT7", "data_type": "uint8", "position": {"byte_offset": 10, "unit": "byte", "len": 1, "bit_offset": 0}, "uint_spec": {"addition": 0, "max": 30, "ratio": 1, "min": 0}, "type": "status_writable", "id": 26, "desc": "\u901a\u90537\u95f4\u9699\u65f6\u95f4"}, {"display_name": "\u95f4\u9699\u65f6\u95f48", "name": "IntervalT8", "data_type": "uint8", "position": {"byte_offset": 11, "unit": "byte", "len": 1, "bit_offset": 0}, "uint_spec": {"addition": 0, "max": 30, "ratio": 1, "min": 0}, "type": "status_writable", "id": 27, "desc": "\u901a\u90538\u95f4\u9699\u65f6\u95f4"}, {"display_name": "\u6821\u51c6\u91cf", "name": "Calib1", "data_type": "uint8", "position": {"byte_offset": 12, "unit": "byte", "len": 1, "bit_offset": 0}, "uint_spec": {"addition": 0, "max": 100, "ratio": 1, "min": 10}, "type": "status_writable", "id": 28, "desc": "\u901a\u9053\u6821\u51c6\u91cf"}, {"display_name": "CH1SWTime", "name": "CH1SWTime", "data_type": "binary", "position": {"byte_offset": 13, "unit": "byte", "len": 96, "bit_offset": 0}, "type": "status_writable", "id": 29, "desc": "\u901a\u90531\u5b9a\u65f6\u65f6\u95f4\u548c\u6d41\u91cf"}, {"display_name": "CH2SWTime", "name": "CH2SWTime", "data_type": "binary", "position": {"byte_offset": 109, "unit": "byte", "len": 96, "bit_offset": 0}, "type": "status_writable", "id": 30, "desc": "\u901a\u90532\u5b9a\u65f6\u65f6\u95f4\u548c\u6d41\u91cf"}, {"display_name": "CH3SWTime", "name": "CH3SWTime", "data_type": "binary", "position": {"byte_offset": 205, "unit": "byte", "len": 96, "bit_offset": 0}, "type": "status_writable", "id": 31, "desc": "\u901a\u90533\u5b9a\u65f6\u65f6\u95f4\u548c\u6d41\u91cf"}, {"display_name": "CH4SWTime", "name": "CH4SWTime", "data_type": "binary", "position": {"byte_offset": 301, "unit": "byte", "len": 96, "bit_offset": 0}, "type": "status_writable", "id": 32, "desc": "\u901a\u90534\u5b9a\u65f6\u65f6\u95f4\u548c\u6d41\u91cf"}, {"display_name": "CH5SWTime", "name": "CH5SWTime", "data_type": "binary", "position": {"byte_offset": 397, "unit": "byte", "len": 96, "bit_offset": 0}, "type": "status_writable", "id": 33, "desc": "\u901a\u90535\u5b9a\u65f6\u65f6\u95f4\u548c\u6d41\u91cf"}, {"display_name": "CH6SWTime", "name": "CH6SWTime", "data_type": "binary", "position": {"byte_offset": 493, "unit": "byte", "len": 96, "bit_offset": 0}, "type": "status_writable", "id": 34, "desc": "\u901a\u90536\u5b9a\u65f6\u65f6\u95f4\u548c\u6d41\u91cf"}, {"display_name": "CH7SWTime", "name": "CH7SWTime", "data_type": "binary", "position": {"byte_offset": 589, "unit": "byte", "len": 96, "bit_offset": 0}, "type": "status_writable", "id": 35, "desc": "\u901a\u90537\u5b9a\u65f6\u65f6\u95f4\u548c\u6d41\u91cf"}, {"display_name": "CH8SWTime", "name": "CH8SWTime", "data_type": "binary", "position": {"byte_offset": 685, "unit": "byte", "len": 96, "bit_offset": 0}, "type": "status_writable", "id": 36, "desc": "\u901a\u90538\u5b9a\u65f6\u65f6\u95f4\u548c\u6d41\u91cf"}, {"display_name": "\u65e5\u671f\u6570\u636e", "name": "YMDData", "data_type": "binary", "position": {"byte_offset": 781, "unit": "byte", "len": 4, "bit_offset": 0}, "type": "status_writable", "id": 37, "desc": "\u65e5\u671f, Byte1\u5e74\u5343\u4f4d\u767e\u4f4d, byte2\u5e74\u5341\u4f4d\u4e2a\u4f4d, byte3\u6708, byte4\u65e5"}, {"display_name": "\u65f6\u95f4\u6570\u636e", "name": "HMSData", "data_type": "binary", "position": {"byte_offset": 785, "unit": "byte", "len": 4, "bit_offset": 0}, "type": "status_writable", "id": 38, "desc": "\u65f6\u95f4, Byte1\u7a7a, byte2\u65f6, byte3\u5206, byte4\u79d2"}, {"display_name": "\u6821\u51c6\u65f6\u95f4", "name": "time1", "data_type": "uint8", "position": {"byte_offset": 789, "unit": "byte", "len": 1, "bit_offset": 0}, "uint_spec": {"addition": 0, "max": 250, "ratio": 1, "min": 10}, "type": "status_readonly", "id": 39, "desc": "\u8865\u7ed9\u6821\u51c6\u91cf\u6240\u9700\u65f6\u95f4,\u5355\u4f4d\u79d2"}, {"display_name": "\u5f00\u8def", "name": "OpenCircuit", "data_type": "bool", "position": {"byte_offset": 790, "unit": "bit", "len": 1, "bit_offset": 0}, "type": "alert", "id": 40, "desc": "\u7ebf\u8def\u65ad\u5f00"}, {"display_name": "\u4e32\u53e3\u8fde\u63a5\u6545\u969c", "name": "Fault_UART", "data_type": "bool", "position": {"byte_offset": 791, "unit": "bit", "len": 1, "bit_offset": 0}, "type": "fault", "id": 41, "desc": "\u6a21\u5757\u4e0e\u4e3b\u677f\u901a\u8baf\u4e0d\u4e0a"}], "name": "entity0", "id": 0}], "ui": {"object": {"version": 4, "showEditButton": false}, "sections": [{"elements": [{"boolValue": false, "object": {"action": "entity0", "bind": ["entity0.switch"], "perm": "W"}, "type": "QBooleanElement", "key": "entity0.switch", "title": "\u5f00\u5173"}, {"boolValue": false, "object": {"action": "entity0", "bind": ["entity0.channe1"], "perm": "W"}, "type": "QBooleanElement", "key": "entity0.channe1", "title": "\u901a\u90531"}, {"boolValue": false, "object": {"action": "entity0", "bind": ["entity0.channe2"], "perm": "W"}, "type": "QBooleanElement", "key": "entity0.channe2", "title": "\u901a\u90532"}, {"boolValue": false, "object": {"action": "entity0", "bind": ["entity0.channe3"], "perm": "W"}, "type": "QBooleanElement", "key": "entity0.channe3", "title": "\u901a\u90533"}, {"boolValue": false, "object": {"action": "entity0", "bind": ["entity0.channe4"], "perm": "W"}, "type": "QBooleanElement", "key": "entity0.channe4", "title": "\u901a\u90534"}, {"boolValue": false, "object": {"action": "entity0", "bind": ["entity0.channe5"], "perm": "W"}, "type": "QBooleanElement", "key": "entity0.channe5", "title": "\u901a\u90535"}, {"boolValue": false, "object": {"action": "entity0", "bind": ["entity0.channe6"], "perm": "W"}, "type": "QBooleanElement", "key": "entity0.channe6", "title": "\u901a\u90536"}, {"boolValue": false, "object": {"action": "entity0", "bind": ["entity0.channe7"], "perm": "W"}, "type": "QBooleanElement", "key": "entity0.channe7", "title": "\u901a\u90537"}, {"boolValue": false, "object": {"action": "entity0", "bind": ["entity0.channe8"], "perm": "W"}, "type": "QBooleanElement", "key": "entity0.channe8", "title": "\u901a\u90538"}, {"boolValue": false, "object": {"action": "entity0", "bind": ["entity0.Timer1ON"], "perm": "W"}, "type": "QBooleanElement", "key": "entity0.Timer1ON", "title": "\u5b9a\u65f6\u5f00\u51731"}, {"boolValue": false, "object": {"action": "entity0", "bind": ["entity0.Timer2ON"], "perm": "W"}, "type": "QBooleanElement", "key": "entity0.Timer2ON", "title": "\u5b9a\u65f6\u5f00\u51732"}, {"boolValue": false, "object": {"action": "entity0", "bind": ["entity0.Timer3ON"], "perm": "W"}, "type": "QBooleanElement", "key": "entity0.Timer3ON", "title": "\u5b9a\u65f6\u5f00\u51733"}, {"boolValue": false, "object": {"action": "entity0", "bind": ["entity0.Timer4ON"], "perm": "W"}, "type": "QBooleanElement", "key": "entity0.Timer4ON", "title": "\u5b9a\u65f6\u5f00\u51734"}, {"boolValue": false, "object": {"action": "entity0", "bind": ["entity0.Timer5ON"], "perm": "W"}, "type": "QBooleanElement", "key": "entity0.Timer5ON", "title": "\u5b9a\u65f6\u5f00\u51735"}, {"boolValue": false, "object": {"action": "entity0", "bind": ["entity0.Timer6ON"], "perm": "W"}, "type": "QBooleanElement", "key": "entity0.Timer6ON", "title": "\u5b9a\u65f6\u5f00\u51736"}, {"boolValue": false, "object": {"action": "entity0", "bind": ["entity0.Timer7ON"], "perm": "W"}, "type": "QBooleanElement", "key": "entity0.Timer7ON", "title": "\u5b9a\u65f6\u5f00\u51737"}, {"boolValue": false, "object": {"action": "entity0", "bind": ["entity0.Timer8ON"], "perm": "W"}, "type": "QBooleanElement", "key": "entity0.Timer8ON", "title": "\u5b9a\u65f6\u5f00\u51738"}, {"boolValue": false, "object": {"action": "entity0", "bind": ["entity0.CALSW"], "perm": "W"}, "type": "QBooleanElement", "key": "entity0.CALSW", "title": "\u6821\u51c6\u5f00\u5173"}, {"items": ["\u6821\u51c61", "\u6821\u51c62", "\u6821\u51c63", "\u6821\u51c64", "\u6821\u51c65", "\u6821\u51c66", "\u6821\u51c67", "\u6821\u51c68"], "object": {"action": "entity0", "bind": ["entity0.CALSet"], "perm": "W"}, "type": "QRadioElement", "key": "entity0.CALSet", "title": "\u6821\u51c6\u901a\u9053"}, {"title": "\u5934\u6570\u91cf", "bind": "floatValue:float", "object": {"action": "entity0", "bind": ["entity0.channelTTL"], "uint_spec": {"max": 8, "step": 1, "min": 1}, "perm": "W"}, "value": 0, "key": "entity0.channelTTL", "maximumValue": 8, "minimumValue": 1, "type": "QFloatElement"}, {"title": "\u95f4\u9699\u65f6\u95f41", "bind": "floatValue:float", "object": {"action": "entity0", "bind": ["entity0.IntervalT1"], "uint_spec": {"max": 30, "step": 1, "min": 0}, "perm": "W"}, "value": 0, "key": "entity0.IntervalT1", "maximumValue": 30, "minimumValue": 0, "type": "QFloatElement"}, {"title": "\u95f4\u9699\u65f6\u95f42", "bind": "floatValue:float", "object": {"action": "entity0", "bind": ["entity0.IntervalT2"], "uint_spec": {"max": 30, "step": 1, "min": 0}, "perm": "W"}, "value": 0, "key": "entity0.IntervalT2", "maximumValue": 30, "minimumValue": 0, "type": "QFloatElement"}, {"title": "\u95f4\u9699\u65f6\u95f43", "bind": "floatValue:float", "object": {"action": "entity0", "bind": ["entity0.IntervalT3"], "uint_spec": {"max": 30, "step": 1, "min": 0}, "perm": "W"}, "value": 0, "key": "entity0.IntervalT3", "maximumValue": 30, "minimumValue": 0, "type": "QFloatElement"}, {"title": "\u95f4\u9699\u65f6\u95f44", "bind": "floatValue:float", "object": {"action": "entity0", "bind": ["entity0.IntervalT4"], "uint_spec": {"max": 30, "step": 1, "min": 0}, "perm": "W"}, "value": 0, "key": "entity0.IntervalT4", "maximumValue": 30, "minimumValue": 0, "type": "QFloatElement"}, {"title": "\u95f4\u9699\u65f6\u95f45", "bind": "floatValue:float", "object": {"action": "entity0", "bind": ["entity0.IntervalT5"], "uint_spec": {"max": 30, "step": 1, "min": 0}, "perm": "W"}, "value": 0, "key": "entity0.IntervalT5", "maximumValue": 30, "minimumValue": 0, "type": "QFloatElement"}, {"title": "\u95f4\u9699\u65f6\u95f46", "bind": "floatValue:float", "object": {"action": "entity0", "bind": ["entity0.IntervalT6"], "uint_spec": {"max": 30, "step": 1, "min": 0}, "perm": "W"}, "value": 0, "key": "entity0.IntervalT6", "maximumValue": 30, "minimumValue": 0, "type": "QFloatElement"}, {"title": "\u95f4\u9699\u65f6\u95f47", "bind": "floatValue:float", "object": {"action": "entity0", "bind": ["entity0.IntervalT7"], "uint_spec": {"max": 30, "step": 1, "min": 0}, "perm": "W"}, "value": 0, "key": "entity0.IntervalT7", "maximumValue": 30, "minimumValue": 0, "type": "QFloatElement"}, {"title": "\u95f4\u9699\u65f6\u95f48", "bind": "floatValue:float", "object": {"action": "entity0", "bind": ["entity0.IntervalT8"], "uint_spec": {"max": 30, "step": 1, "min": 0}, "perm": "W"}, "value": 0, "key": "entity0.IntervalT8", "maximumValue": 30, "minimumValue": 0, "type": "QFloatElement"}, {"title": "\u6821\u51c6\u91cf", "bind": "floatValue:float", "object": {"action": "entity0", "bind": ["entity0.Calib1"], "uint_spec": {"max": 100, "step": 1, "min": 10}, "perm": "W"}, "value": 0, "key": "entity0.Calib1", "maximumValue": 100, "minimumValue": 10, "type": "QFloatElement"}, {"keyboardType": "NumbersAndPunctuation", "title": "CH1SWTime", "object": {"action": "entity0", "bind": ["entity0.CH1SWTime"], "perm": "W"}, "value": 0, "key": "entity0.CH1SWTime", "maxLength": 192, "type": "QMultilineElement"}, {"keyboardType": "NumbersAndPunctuation", "title": "CH2SWTime", "object": {"action": "entity0", "bind": ["entity0.CH2SWTime"], "perm": "W"}, "value": 0, "key": "entity0.CH2SWTime", "maxLength": 192, "type": "QMultilineElement"}, {"keyboardType": "NumbersAndPunctuation", "title": "CH3SWTime", "object": {"action": "entity0", "bind": ["entity0.CH3SWTime"], "perm": "W"}, "value": 0, "key": "entity0.CH3SWTime", "maxLength": 192, "type": "QMultilineElement"}, {"keyboardType": "NumbersAndPunctuation", "title": "CH4SWTime", "object": {"action": "entity0", "bind": ["entity0.CH4SWTime"], "perm": "W"}, "value": 0, "key": "entity0.CH4SWTime", "maxLength": 192, "type": "QMultilineElement"}, {"keyboardType": "NumbersAndPunctuation", "title": "CH5SWTime", "object": {"action": "entity0", "bind": ["entity0.CH5SWTime"], "perm": "W"}, "value": 0, "key": "entity0.CH5SWTime", "maxLength": 192, "type": "QMultilineElement"}, {"keyboardType": "NumbersAndPunctuation", "title": "CH6SWTime", "object": {"action": "entity0", "bind": ["entity0.CH6SWTime"], "perm": "W"}, "value": 0, "key": "entity0.CH6SWTime", "maxLength": 192, "type": "QMultilineElement"}, {"keyboardType": "NumbersAndPunctuation", "title": "CH7SWTime", "object": {"action": "entity0", "bind": ["entity0.CH7SWTime"], "perm": "W"}, "value": 0, "key": "entity0.CH7SWTime", "maxLength": 192, "type": "QMultilineElement"}, {"keyboardType": "NumbersAndPunctuation", "title": "CH8SWTime", "object": {"action": "entity0", "bind": ["entity0.CH8SWTime"], "perm": "W"}, "value": 0, "key": "entity0.CH8SWTime", "maxLength": 192, "type": "QMultilineElement"}, {"keyboardType": "NumbersAndPunctuation", "title": "\u65e5\u671f\u6570\u636e", "object": {"action": "entity0", "bind": ["entity0.YMDData"], "perm": "W"}, "value": 0, "key": "entity0.YMDData", "maxLength": 8, "type": "QMultilineElement"}, {"keyboardType": "NumbersAndPunctuation", "title": "\u65f6\u95f4\u6570\u636e", "object": {"action": "entity0", "bind": ["entity0.HMSData"], "perm": "W"}, "value": 0, "key": "entity0.HMSData", "maxLength": 8, "type": "QMultilineElement"}, {"object": {"action": "entity0", "bind": ["entity0.time1"], "uint_spec": {"max": 250, "step": 1, "min": 10}, "perm": "N"}, "type": "QLabelElement", "key": "entity0.time1", "title": "\u6821\u51c6\u65f6\u95f4"}]}]}}